pyspark_val/__init__.py
pyspark_val/_backwards.py
pyspark_val/assertion.py
pyspark_val/create.py
pyspark_val/mock.py
pyspark_val-0.1.4.dist-info/LICENSE
pyspark_val-0.1.4.dist-info/METADATA
pyspark_val-0.1.4.dist-info/WHEEL
pyspark_val-0.1.4.dist-info/top_level.txt
pyspark_val-0.1.4.dist-info/RECORD
