Metadata-Version: 2.1
Name: pyspark_val
Version: 0.1.4
Summary: PySpark validation & testing tooling
Home-page: https://github.com/CarterFendley/pyspark-val
Author: Rahul Kumar, Carter Fendley
License: MIT
Keywords: assert pyspark unit test testing compare validation
License-File: LICENSE
Requires-Dist: pyspark >=2.1.2
